[
  {
    "text": "Couto [Raiders] (543 pts)",
    "children": [
      {
        "text": "DB (Top 3)",
        "children": [
          {
            "text": "KAMARI LASSITER (14 pts)"
          },
          {
            "text": "TYSON CAMPBELL (10 pts)"
          },
          {
            "text": "SAUCE GARDNER (0 pts)"
          },
          {
            "text": "DEVON WITHERSPOON (0 pts)"
          },
          {
            "text": "Riq Woolen (0 pts)"
          },
          {
            "text": "Pat Surtain II (0 pts)"
          }
        ]
      },
      {
        "text": "DL (Top 3)",
        "children": [
          {
            "text": "MYLES GARRETT (60 pts)"
          },
          {
            "text": "DANIELLE HUNTER (36 pts)"
          },
          {
            "text": "DEVONTE WYATT (8 pts)"
          },
          {
            "text": "BRYAN BRESEE (6 pts)"
          },
          {
            "text": "KOBIE TURNER (6 pts)"
          },
          {
            "text": "KEION WHITE (2 pts)"
          }
        ]
      },
      {
        "text": "K (Top 1)",
        "children": [
          {
            "text": "WILL REICHARD (38 pts)"
          },
          {
            "text": "JOSHUA KARTY (20 pts)"
          }
        ]
      },
      {
        "text": "LB (Top 2)",
        "children": [
          {
            "text": "T.J. WATT (34 pts)"
          },
          {
            "text": "KADEN ELLISS (30 pts)"
          },
          {
            "text": "JAELAN PHILLIPS (23 pts)"
          },
          {
            "text": "YAYA DIABY (21 pts)"
          },
          {
            "text": "CHOP ROBINSON (5 pts)"
          }
        ]
      },
      {
        "text": "QB (Top 2)",
        "children": [
          {
            "text": "DAK PRESCOTT (51 pts)"
          },
          {
            "text": "JARED GOFF (45 pts)"
          },
          {
            "text": "MICHAEL PENIX JR. (31 pts)"
          }
        ]
      },
      {
        "text": "RB (Top 2)",
        "children": [
          {
            "text": "JONATHAN TAYLOR (77 pts)"
          },
          {
            "text": "JAMES COOK (44 pts)"
          },
          {
            "text": "CHASE BROWN (23 pts)"
          },
          {
            "text": "TONY POLLARD (18 pts)"
          },
          {
            "text": "BRAELON ALLEN (3 pts)"
          }
        ]
      },
      {
        "text": "TE (Top 1)",
        "children": [
          {
            "text": "DALLAS GOEDERT (36 pts)"
          },
          {
            "text": "BROCK BOWERS (29 pts)"
          },
          {
            "text": "DAVID NJOKU (19 pts)"
          }
        ]
      },
      {
        "text": "WR (Top 3)",
        "children": [
          {
            "text": "KHALIL SHAKIR (21 pts)"
          },
          {
            "text": "A.J. BROWN (21 pts)"
          },
          {
            "text": "JAUAN JENNINGS (18 pts)"
          },
          {
            "text": "COOPER KUPP (12 pts)"
          },
          {
            "text": "RICKY PEARSALL (9 pts)"
          },
          {
            "text": "JAYDEN REED (3 pts)"
          }
        ]
      }
    ]
  },
  {
    "text": "Mass [Bengals] (539 pts)",
    "children": [
      {
        "text": "DB (Top 3)",
        "children": [
          {
            "text": "NATE WIGGINS (21 pts)"
          },
          {
            "text": "NICK CROSS (7 pts)"
          },
          {
            "text": "TYRIQUE STEVENSON (7 pts)"
          },
          {
            "text": "JADEN HICKS (0 pts)"
          },
          {
            "text": "TARHEEB STILL (0 pts)"
          },
          {
            "text": "ANDRE CISCO (0 pts)"
          }
        ]
      },
      {
        "text": "DL (Top 3)",
        "children": [
          {
            "text": "MONTEZ SWEAT (22 pts)"
          },
          {
            "text": "Josh Hines-Allen (12 pts)"
          },
          {
            "text": "TYREE WILSON (8 pts)"
          },
          {
            "text": "DARIUS ROBINSON (4 pts)"
          },
          {
            "text": "Isaiah McGuire (4 pts)"
          },
          {
            "text": "MARCUS DAVENPORT (4 pts)"
          }
        ]
      },
      {
        "text": "K (Top 1)",
        "children": [
          {
            "text": "CHASE MCLAUGHLIN (40 pts)"
          },
          {
            "text": "DANIEL CARLSON (30 pts)"
          }
        ]
      },
      {
        "text": "LB (Top 2)",
        "children": [
          {
            "text": "NIK BONITTO (44 pts)"
          },
          {
            "text": "BRADLEY CHUBB (26 pts)"
          },
          {
            "text": "FOYE OLUOKUN (23 pts)"
          },
          {
            "text": "TERREL BERNARD (13 pts)"
          }
        ]
      },
      {
        "text": "QB (Top 2)",
        "children": [
          {
            "text": "DANIEL JONES (58 pts)"
          },
          {
            "text": "JUSTIN HERBERT (54 pts)"
          },
          {
            "text": "CALEB WILLIAMS (49 pts)"
          }
        ]
      },
      {
        "text": "RB (Top 2)",
        "children": [
          {
            "text": "JAVONTE WILLIAMS (43 pts)"
          },
          {
            "text": "BIJAN ROBINSON (42 pts)"
          },
          {
            "text": "DERRICK HENRY (37 pts)"
          },
          {
            "text": "J.K. DOBBINS (26 pts)"
          },
          {
            "text": "TYLER ALLGEIER (25 pts)"
          }
        ]
      },
      {
        "text": "TE (Top 1)",
        "children": [
          {
            "text": "TREY MCBRIDE (56 pts)"
          },
          {
            "text": "ISAIAH LIKELY (5 pts)"
          },
          {
            "text": "BEN SINNOTT (3 pts)"
          }
        ]
      },
      {
        "text": "WR (Top 3)",
        "children": [
          {
            "text": "JAXON SMITH-NJIGBA (48 pts)"
          },
          {
            "text": "Deebo Samuel Sr. (30 pts)"
          },
          {
            "text": "GARRETT WILSON (21 pts)"
          },
          {
            "text": "JERRY JEUDY (12 pts)"
          },
          {
            "text": "CHRIS GODWIN Jr. (0 pts)"
          }
        ]
      }
    ]
  },
  {
    "text": "Jumps [Packers] (528 pts)",
    "children": [
      {
        "text": "DB (Top 3)",
        "children": [
          {
            "text": "JALEN PITRE (21 pts)"
          },
          {
            "text": "KERBY JOSEPH (21 pts)"
          },
          {
            "text": "KAMREN KINCHENS (14 pts)"
          },
          {
            "text": "CALEN BULLOCK (14 pts)"
          },
          {
            "text": "JOEY PORTER JR. (7 pts)"
          },
          {
            "text": "JAYLON JOHNSON (0 pts)"
          }
        ]
      },
      {
        "text": "DL (Top 3)",
        "children": [
          {
            "text": "AIDAN HUTCHINSON (30 pts)"
          },
          {
            "text": "Will McDonald IV (28 pts)"
          },
          {
            "text": "LEONARD WILLIAMS (20 pts)"
          },
          {
            "text": "BRYCE HUFF (16 pts)"
          },
          {
            "text": "JAVON HARGRAVE (12 pts)"
          },
          {
            "text": "BRADEN FISKE (4 pts)"
          }
        ]
      },
      {
        "text": "K (Top 1)",
        "children": [
          {
            "text": "HARRISON BUTKER (32 pts)"
          },
          {
            "text": "YOUNGHOE KOO (8 pts)"
          }
        ]
      },
      {
        "text": "LB (Top 2)",
        "children": [
          {
            "text": "BYRON YOUNG (46 pts)"
          },
          {
            "text": "HAROLD LANDRY III (29 pts)"
          },
          {
            "text": "FRANKIE LUVU (19 pts)"
          },
          {
            "text": "JONATHAN GREENARD (14 pts)"
          },
          {
            "text": "AZEEZ OJULARI (1 pts)"
          }
        ]
      },
      {
        "text": "QB (Top 2)",
        "children": [
          {
            "text": "MATTHEW STAFFORD (52 pts)"
          },
          {
            "text": "TREVOR LAWRENCE (49 pts)"
          },
          {
            "text": "KYLER MURRAY (20 pts)"
          }
        ]
      },
      {
        "text": "RB (Top 2)",
        "children": [
          {
            "text": "RICO DOWDLE (36 pts)"
          },
          {
            "text": "ALVIN KAMARA (13 pts)"
          },
          {
            "text": "RAY DAVIS (3 pts)"
          },
          {
            "text": "JEROME FORD (0 pts)"
          }
        ]
      },
      {
        "text": "TE (Top 1)",
        "children": [
          {
            "text": "HUNTER HENRY (32 pts)"
          },
          {
            "text": "T.J. HOCKENSON (16 pts)"
          },
          {
            "text": "NOAH GRAY (5 pts)"
          }
        ]
      },
      {
        "text": "WR (Top 3)",
        "children": [
          {
            "text": "PUKA NACUA (39 pts)"
          },
          {
            "text": "TEE HIGGINS (36 pts)"
          },
          {
            "text": "JAMESON WILLIAMS (30 pts)"
          },
          {
            "text": "COURTLAND SUTTON (30 pts)"
          },
          {
            "text": "MARVIN HARRISON JR. (27 pts)"
          },
          {
            "text": "CHRISTIAN WATSON (12 pts)"
          }
        ]
      }
    ]
  },
  {
    "text": "Chris [Bears] (494 pts)",
    "children": [
      {
        "text": "DB (Top 3)",
        "children": [
          {
            "text": "DARON BLAND (10 pts)"
          },
          {
            "text": "GENO STONE (7 pts)"
          },
          {
            "text": "MARLON HUMPHREY (7 pts)"
          },
          {
            "text": "ALONTAE TAYLOR (7 pts)"
          },
          {
            "text": "TALANOA HUFANGA (0 pts)"
          },
          {
            "text": "TREVON DIGGS (0 pts)"
          }
        ]
      },
      {
        "text": "DL (Top 3)",
        "children": [
          {
            "text": "MAXX CROSBY (24 pts)"
          },
          {
            "text": "GEORGE KARLAFTIS (20 pts)"
          },
          {
            "text": "MORO OJOMO (16 pts)"
          },
          {
            "text": "CHRIS JONES (12 pts)"
          },
          {
            "text": "ALIM MCNEILL (0 pts)"
          }
        ]
      },
      {
        "text": "K (Top 1)",
        "children": [
          {
            "text": "KA'IMI FAIRBAIRN (44 pts)"
          },
          {
            "text": "CHAD RYLAND (32 pts)"
          }
        ]
      },
      {
        "text": "LB (Top 2)",
        "children": [
          {
            "text": "TULI TUIPULOTU (37 pts)"
          },
          {
            "text": "HAASON REDDICK (9 pts)"
          },
          {
            "text": "BOYE MAFE (7 pts)"
          }
        ]
      },
      {
        "text": "QB (Top 2)",
        "children": [
          {
            "text": "JOSH ALLEN (78 pts)"
          },
          {
            "text": "GENO SMITH (34 pts)"
          },
          {
            "text": "SPENCER RATTLER (25 pts)"
          }
        ]
      },
      {
        "text": "RB (Top 2)",
        "children": [
          {
            "text": "CHRISTIAN MCCAFFREY (61 pts)"
          },
          {
            "text": "DE'VON ACHANE (51 pts)"
          },
          {
            "text": "JAMES CONNER (6 pts)"
          },
          {
            "text": "ROSCHON JOHNSON (0 pts)"
          },
          {
            "text": "RAHEEM MOSTERT (0 pts)"
          }
        ]
      },
      {
        "text": "TE (Top 1)",
        "children": [
          {
            "text": "THEO JOHNSON (30 pts)"
          },
          {
            "text": "GEORGE KITTLE (25 pts)"
          }
        ]
      },
      {
        "text": "WR (Top 3)",
        "children": [
          {
            "text": "STEFON DIGGS (27 pts)"
          },
          {
            "text": "RASHID SHAHEED (21 pts)"
          },
          {
            "text": "BRIAN THOMAS JR. (18 pts)"
          },
          {
            "text": "RASHOD BATEMAN (9 pts)"
          },
          {
            "text": "ADONAI MITCHELL (3 pts)"
          },
          {
            "text": "CHRISTIAN KIRK (3 pts)"
          }
        ]
      }
    ]
  },
  {
    "text": "Marco [Eagles] (491 pts)",
    "children": [
      {
        "text": "DB (Top 3)",
        "children": [
          {
            "text": "MIKE SAINRISTIL (21 pts)"
          },
          {
            "text": "CAMRYN BYNUM (14 pts)"
          },
          {
            "text": "MARSHON LATTIMORE (7 pts)"
          },
          {
            "text": "REED BLANKENSHIP (0 pts)"
          },
          {
            "text": "Cam Taylor-Britt (0 pts)"
          },
          {
            "text": "JI'AYIR BROWN (0 pts)"
          }
        ]
      },
      {
        "text": "DL (Top 3)",
        "children": [
          {
            "text": "WILL ANDERSON JR. (32 pts)"
          },
          {
            "text": "RASHAN GARY (30 pts)"
          },
          {
            "text": "LAIATU LATU (20 pts)"
          },
          {
            "text": "LUKAS VAN NESS (6 pts)"
          },
          {
            "text": "JALEN CARTER (4 pts)"
          },
          {
            "text": "DEXTER LAWRENCE (2 pts)"
          }
        ]
      },
      {
        "text": "K (Top 1)",
        "children": [
          {
            "text": "CAM LITTLE (32 pts)"
          },
          {
            "text": "JAKE BATES (26 pts)"
          }
        ]
      },
      {
        "text": "LB (Top 2)",
        "children": [
          {
            "text": "JONATHON COOPER (36 pts)"
          },
          {
            "text": "ANDREW VAN GINKEL (16 pts)"
          },
          {
            "text": "JALYX HUNT (16 pts)"
          },
          {
            "text": "ARDEN KEY (13 pts)"
          },
          {
            "text": "ROQUAN SMITH (13 pts)"
          }
        ]
      },
      {
        "text": "QB (Top 2)",
        "children": [
          {
            "text": "BO NIX (55 pts)"
          },
          {
            "text": "BAKER MAYFIELD (45 pts)"
          },
          {
            "text": "TUA TAGOVAILOA (38 pts)"
          }
        ]
      },
      {
        "text": "RB (Top 2)",
        "children": [
          {
            "text": "KYREN WILLIAMS (43 pts)"
          },
          {
            "text": "ZACH CHARBONNET (24 pts)"
          },
          {
            "text": "NICK CHUBB (14 pts)"
          },
          {
            "text": "ISIAH PACHECO (12 pts)"
          },
          {
            "text": "NAJEE HARRIS (0 pts)"
          }
        ]
      },
      {
        "text": "TE (Top 1)",
        "children": [
          {
            "text": "TUCKER KRAFT (38 pts)"
          },
          {
            "text": "MARK ANDREWS (25 pts)"
          },
          {
            "text": "DALTON SCHULTZ (23 pts)"
          }
        ]
      },
      {
        "text": "WR (Top 3)",
        "children": [
          {
            "text": "MICHAEL PITTMAN (33 pts)"
          },
          {
            "text": "JUSTIN JEFFERSON (27 pts)"
          },
          {
            "text": "JOSH DOWNS (18 pts)"
          },
          {
            "text": "RASHEE RICE (18 pts)"
          },
          {
            "text": "CALVIN RIDLEY (9 pts)"
          },
          {
            "text": "MIKE EVANS (6 pts)"
          }
        ]
      }
    ]
  },
  {
    "text": "Denny [Vikings] (486 pts)",
    "children": [
      {
        "text": "DB (Top 3)",
        "children": [
          {
            "text": "JAYCEE HORN (21 pts)"
          },
          {
            "text": "KENNY MOORE II (10 pts)"
          },
          {
            "text": "JALEN RAMSEY (7 pts)"
          },
          {
            "text": "DENZEL WARD (7 pts)"
          },
          {
            "text": "TERRION ARNOLD (7 pts)"
          },
          {
            "text": "BRIAN BRANCH (0 pts)"
          }
        ]
      },
      {
        "text": "DL (Top 3)",
        "children": [
          {
            "text": "ZACH ALLEN (24 pts)"
          },
          {
            "text": "CARL GRANDERSON (18 pts)"
          },
          {
            "text": "TREY HENDRICKSON (16 pts)"
          },
          {
            "text": "CHASE YOUNG (12 pts)"
          },
          {
            "text": "TRAVON WALKER (10 pts)"
          },
          {
            "text": "SAM WILLIAMS (4 pts)"
          }
        ]
      },
      {
        "text": "K (Top 1)",
        "children": [
          {
            "text": "CAMERON DICKER (50 pts)"
          },
          {
            "text": "MATT GAY (26 pts)"
          }
        ]
      },
      {
        "text": "LB (Top 2)",
        "children": [
          {
            "text": "MICAH PARSONS (37 pts)"
          },
          {
            "text": "ZAIRE FRANKLIN (20 pts)"
          },
          {
            "text": "CHRIS BRASWELL (4 pts)"
          },
          {
            "text": "DERICK HALL (3 pts)"
          },
          {
            "text": "DAVID OJABO (3 pts)"
          }
        ]
      },
      {
        "text": "QB (Top 2)",
        "children": [
          {
            "text": "JALEN HURTS (57 pts)"
          },
          {
            "text": "SAM DARNOLD (42 pts)"
          },
          {
            "text": "LAMAR JACKSON (36 pts)"
          }
        ]
      },
      {
        "text": "RB (Top 2)",
        "children": [
          {
            "text": "TRAVIS ETIENNE (34 pts)"
          },
          {
            "text": "SAQUON BARKLEY (34 pts)"
          },
          {
            "text": "JORDAN MASON (23 pts)"
          },
          {
            "text": "CHUBA HUBBARD (17 pts)"
          },
          {
            "text": "RHAMONDRE STEVENSON (15 pts)"
          }
        ]
      },
      {
        "text": "TE (Top 1)",
        "children": [
          {
            "text": "SAM LAPORTA (29 pts)"
          },
          {
            "text": "KYLE PITTS (23 pts)"
          },
          {
            "text": "JA'TAVION SANDERS (5 pts)"
          }
        ]
      },
      {
        "text": "WR (Top 3)",
        "children": [
          {
            "text": "QUENTIN JOHNSTON (33 pts)"
          },
          {
            "text": "CHRIS OLAVE (30 pts)"
          },
          {
            "text": "ZAY FLOWERS (24 pts)"
          },
          {
            "text": "KEON COLEMAN (18 pts)"
          },
          {
            "text": "XAVIER WORTHY (9 pts)"
          },
          {
            "text": "TERRY MCLAURIN (9 pts)"
          }
        ]
      }
    ]
  },
  {
    "text": "Tony [Cowboys] (464 pts)",
    "children": [
      {
        "text": "DB (Top 3)",
        "children": [
          {
            "text": "KEVIN BYARD (35 pts)"
          },
          {
            "text": "TRENT MCDUFFIE (7 pts)"
          },
          {
            "text": "QUAN MARTIN (0 pts)"
          },
          {
            "text": "JULIAN BLACKMON (0 pts)"
          },
          {
            "text": "TYLER NUBIN (0 pts)"
          }
        ]
      },
      {
        "text": "DL (Top 3)",
        "children": [
          {
            "text": "DORANCE ARMSTRONG (22 pts)"
          },
          {
            "text": "ALEX WRIGHT (12 pts)"
          },
          {
            "text": "KWITY PAYE (12 pts)"
          },
          {
            "text": "MYLES MURPHY (10 pts)"
          },
          {
            "text": "MARSHAWN KNEELAND (4 pts)"
          },
          {
            "text": "MALCOLM KOONCE (4 pts)"
          }
        ]
      },
      {
        "text": "K (Top 1)",
        "children": [
          {
            "text": "JASON MYERS (42 pts)"
          },
          {
            "text": "GRAHAM GANO (18 pts)"
          }
        ]
      },
      {
        "text": "LB (Top 2)",
        "children": [
          {
            "text": "BRIAN BURNS (62 pts)"
          },
          {
            "text": "JERMAINE JOHNSON II (17 pts)"
          },
          {
            "text": "DALLAS TURNER (17 pts)"
          },
          {
            "text": "ARNOLD EBIKETIE (9 pts)"
          },
          {
            "text": "MATTHEW JUDON (2 pts)"
          }
        ]
      },
      {
        "text": "QB (Top 2)",
        "children": [
          {
            "text": "JORDAN LOVE (41 pts)"
          },
          {
            "text": "JAYDEN DANIELS (29 pts)"
          },
          {
            "text": "ANTHONY RICHARDSON (0 pts)"
          }
        ]
      },
      {
        "text": "RB (Top 2)",
        "children": [
          {
            "text": "Kenneth Walker III (26 pts)"
          },
          {
            "text": "TYJAE SPEARS (7 pts)"
          },
          {
            "text": "TANK BIGSBY (2 pts)"
          },
          {
            "text": "JAYLEN WRIGHT (0 pts)"
          }
        ]
      },
      {
        "text": "TE (Top 1)",
        "children": [
          {
            "text": "JAKE FERGUSON (41 pts)"
          },
          {
            "text": "PAT FREIERMUTH (19 pts)"
          },
          {
            "text": "CADE OTTON (15 pts)"
          }
        ]
      },
      {
        "text": "WR (Top 3)",
        "children": [
          {
            "text": "DAVANTE ADAMS (45 pts)"
          },
          {
            "text": "ROME ODUNZE (36 pts)"
          },
          {
            "text": "DK METCALF (30 pts)"
          },
          {
            "text": "CEEDEE LAMB (21 pts)"
          },
          {
            "text": "Marvin Mims Jr. (12 pts)"
          },
          {
            "text": "JOSH PALMER (6 pts)"
          }
        ]
      }
    ]
  },
  {
    "text": "Super Dave [Steelers] (441 pts)",
    "children": [
      {
        "text": "DB (Top 3)",
        "children": [
          {
            "text": "DEREK STINGLEY JR. (21 pts)"
          },
          {
            "text": "JESSIE BATES (14 pts)"
          },
          {
            "text": "BYRON MURPHY (0 pts)"
          },
          {
            "text": "PAULSON ADEBO (0 pts)"
          },
          {
            "text": "A.J. TERRELL (0 pts)"
          },
          {
            "text": "QUINYON MITCHELL (0 pts)"
          }
        ]
      },
      {
        "text": "DL (Top 3)",
        "children": [
          {
            "text": "DEFOREST BUCKNER (16 pts)"
          },
          {
            "text": "ED OLIVER (12 pts)"
          },
          {
            "text": "A.J. EPENESA (10 pts)"
          },
          {
            "text": "NICK BOSA (8 pts)"
          },
          {
            "text": "CAMERON HEYWARD (6 pts)"
          },
          {
            "text": "MICHAEL DANNA (4 pts)"
          }
        ]
      },
      {
        "text": "K (Top 1)",
        "children": [
          {
            "text": "WIL LUTZ (34 pts)"
          },
          {
            "text": "JAKE ELLIOTT (22 pts)"
          }
        ]
      },
      {
        "text": "LB (Top 2)",
        "children": [
          {
            "text": "BOBBY WAGNER (32 pts)"
          },
          {
            "text": "ALEX HIGHSMITH (26 pts)"
          },
          {
            "text": "JOEY BOSA (20 pts)"
          },
          {
            "text": "KHALIL MACK (18 pts)"
          },
          {
            "text": "KYLE VAN NOY (10 pts)"
          }
        ]
      },
      {
        "text": "QB (Top 2)",
        "children": [
          {
            "text": "PATRICK MAHOMES (60 pts)"
          },
          {
            "text": "AARON RODGERS (38 pts)"
          },
          {
            "text": "BRYCE YOUNG (36 pts)"
          }
        ]
      },
      {
        "text": "RB (Top 2)",
        "children": [
          {
            "text": "JAYLEN WARREN (23 pts)"
          },
          {
            "text": "RACHAAD WHITE (20 pts)"
          },
          {
            "text": "BUCKY IRVING (12 pts)"
          },
          {
            "text": "BRIAN ROBINSON (10 pts)"
          },
          {
            "text": "TREY BENSON (2 pts)"
          }
        ]
      },
      {
        "text": "TE (Top 1)",
        "children": [
          {
            "text": "TRAVIS KELCE (42 pts)"
          },
          {
            "text": "ZACH ERTZ (27 pts)"
          },
          {
            "text": "JONNU SMITH (11 pts)"
          }
        ]
      },
      {
        "text": "WR (Top 3)",
        "children": [
          {
            "text": "JAYLEN WADDLE (36 pts)"
          },
          {
            "text": "LADD MCCONKEY (30 pts)"
          },
          {
            "text": "KEENAN ALLEN (27 pts)"
          },
          {
            "text": "JORDAN ADDISON (21 pts)"
          },
          {
            "text": "JAKOBI MEYERS (12 pts)"
          },
          {
            "text": "TYREEK HILL (9 pts)"
          }
        ]
      }
    ]
  },
  {
    "text": "Mario [Jets] (435 pts)",
    "children": [
      {
        "text": "DB (Top 3)",
        "children": [
          {
            "text": "XAVIER MCKINNEY (14 pts)"
          },
          {
            "text": "JOSH JOBE (7 pts)"
          },
          {
            "text": "JEVON HOLLAND (0 pts)"
          },
          {
            "text": "KEISEAN NIXON (0 pts)"
          },
          {
            "text": "JULIAN LOVE (0 pts)"
          },
          {
            "text": "KYLE HAMILTON (0 pts)"
          }
        ]
      },
      {
        "text": "DL (Top 3)",
        "children": [
          {
            "text": "DEMARCUS LAWRENCE (16 pts)"
          },
          {
            "text": "JONATHAN ALLEN (10 pts)"
          },
          {
            "text": "Nnamdi Madubuike (8 pts)"
          },
          {
            "text": "ZACH SIELER (4 pts)"
          },
          {
            "text": "ROY ROBERTSON-HARRIS (0 pts)"
          },
          {
            "text": "CALIJAH KANCEY (0 pts)"
          }
        ]
      },
      {
        "text": "K (Top 1)",
        "children": [
          {
            "text": "CHRIS BOSWELL (38 pts)"
          }
        ]
      },
      {
        "text": "LB (Top 2)",
        "children": [
          {
            "text": "JOSH SWEAT (39 pts)"
          },
          {
            "text": "JARED VERSE (23 pts)"
          },
          {
            "text": "ODAFE OWEH (21 pts)"
          },
          {
            "text": "AZEEZ AL-SHAAIR (13 pts)"
          },
          {
            "text": "Dante Fowler Jr. (9 pts)"
          }
        ]
      },
      {
        "text": "QB (Top 2)",
        "children": [
          {
            "text": "JUSTIN FIELDS (37 pts)"
          },
          {
            "text": "C.J. STROUD (30 pts)"
          },
          {
            "text": "J.J. MCCARTHY (22 pts)"
          }
        ]
      },
      {
        "text": "RB (Top 2)",
        "children": [
          {
            "text": "JOSH JACOBS (49 pts)"
          },
          {
            "text": "BREECE HALL (27 pts)"
          },
          {
            "text": "TYRONE TRACY JR. (11 pts)"
          },
          {
            "text": "DEVIN SINGLETARY (8 pts)"
          },
          {
            "text": "EMANUEL WILSON (7 pts)"
          }
        ]
      },
      {
        "text": "TE (Top 1)",
        "children": [
          {
            "text": "DARREN WALLER (17 pts)"
          },
          {
            "text": "EVAN ENGRAM (13 pts)"
          },
          {
            "text": "MIKE GESICKI (0 pts)"
          }
        ]
      },
      {
        "text": "WR (Top 3)",
        "children": [
          {
            "text": "GEORGE PICKENS (48 pts)"
          },
          {
            "text": "DRAKE LONDON (42 pts)"
          },
          {
            "text": "NICO COLLINS (30 pts)"
          },
          {
            "text": "ROMEO DOUBS (24 pts)"
          },
          {
            "text": "MALIK NABERS (12 pts)"
          },
          {
            "text": "DARNELL MOONEY (6 pts)"
          }
        ]
      }
    ]
  },
  {
    "text": "Rizzo [Colts] (434 pts)",
    "children": [
      {
        "text": "DB (Top 3)",
        "children": [
          {
            "text": "DERWIN JAMES (7 pts)"
          },
          {
            "text": "AMANI HOOKER (0 pts)"
          },
          {
            "text": "L'JARIUS SNEED (0 pts)"
          },
          {
            "text": "C.J. Gardner-Johnson (0 pts)"
          },
          {
            "text": "JAIRE ALEXANDER (0 pts)"
          },
          {
            "text": "CHRISTIAN GONZALEZ (0 pts)"
          }
        ]
      },
      {
        "text": "DL (Top 3)",
        "children": [
          {
            "text": "JEFFERY SIMMONS (22 pts)"
          },
          {
            "text": "Greg ROUSSEAU (12 pts)"
          },
          {
            "text": "QUINNEN WILLIAMS (10 pts)"
          },
          {
            "text": "LEONARD FLOYD (6 pts)"
          },
          {
            "text": "DARON PAYNE (4 pts)"
          },
          {
            "text": "CHRISTIAN BARMORE (4 pts)"
          }
        ]
      },
      {
        "text": "K (Top 1)",
        "children": [
          {
            "text": "BRANDON AUBREY (36 pts)"
          },
          {
            "text": "JAKE MOODY (18 pts)"
          }
        ]
      },
      {
        "text": "LB (Top 2)",
        "children": [
          {
            "text": "JACK CAMPBELL (35 pts)"
          },
          {
            "text": "EDGERRIN COOPER (16 pts)"
          },
          {
            "text": "KAYVON THIBODEAUX (15 pts)"
          },
          {
            "text": "JONAH ELLISS (6 pts)"
          },
          {
            "text": "NOLAN SMITH (6 pts)"
          }
        ]
      },
      {
        "text": "QB (Top 2)",
        "children": [
          {
            "text": "DRAKE MAYE (58 pts)"
          },
          {
            "text": "BROCK PURDY (14 pts)"
          },
          {
            "text": "JOE BURROW (3 pts)"
          }
        ]
      },
      {
        "text": "RB (Top 2)",
        "children": [
          {
            "text": "JAHMYR GIBBS (50 pts)"
          },
          {
            "text": "D'ANDRE SWIFT (31 pts)"
          },
          {
            "text": "DAVID MONTGOMERY (25 pts)"
          },
          {
            "text": "AARON JONES (12 pts)"
          },
          {
            "text": "BLAKE CORUM (9 pts)"
          }
        ]
      },
      {
        "text": "TE (Top 1)",
        "children": [
          {
            "text": "DALTON KINCAID (32 pts)"
          },
          {
            "text": "Chig OKONKWO (15 pts)"
          },
          {
            "text": "BRENTON STRANGE (10 pts)"
          }
        ]
      },
      {
        "text": "WR (Top 3)",
        "children": [
          {
            "text": "AMON-RA ST. BROWN (45 pts)"
          },
          {
            "text": "JA'MARR CHASE (39 pts)"
          },
          {
            "text": "DEVONTA SMITH (27 pts)"
          },
          {
            "text": "DJ MOORE (18 pts)"
          },
          {
            "text": "XAVIER LEGETTE (15 pts)"
          },
          {
            "text": "DONTAYVION WICKS (3 pts)"
          }
        ]
      }
    ]
  }
]